sensorflow/__init__.py
sensorflow/messenger.py
sensorflow/model.py
sensorflow-2.4.dist-info/DESCRIPTION.rst
sensorflow-2.4.dist-info/METADATA
sensorflow-2.4.dist-info/RECORD
sensorflow-2.4.dist-info/WHEEL
sensorflow-2.4.dist-info/metadata.json
sensorflow-2.4.dist-info/top_level.txt
