Metadata-Version: 2.0
Name: sensorflow
Version: 2.4
Summary: Python driver for sensorflow devices
Home-page: https://github.com/Sensorflow/client-python
Author: Alvaro Garcia Gomez
Author-email: maxpowel@gmail.com
License: UNKNOWN
Download-URL: https://github.com/Sensorflow/client-python/archive/master.zip
Keywords: sensor,data
Platform: UNKNOWN
Classifier: Topic :: Adaptive Technologies
Requires-Dist: protocol-buffers-stream
